talklabs/__init__.py
talklabs/tts.py
talklabs-2.1.8.dist-info/licenses/LICENSE
talklabs-2.1.8.dist-info/METADATA
talklabs-2.1.8.dist-info/WHEEL
talklabs-2.1.8.dist-info/top_level.txt
talklabs-2.1.8.dist-info/RECORD
